swh/__init__.py
swh/mirror/__init__.py
swh.mirror.forge-0.0.5.dist-info/AUTHORS
swh.mirror.forge-0.0.5.dist-info/LICENSE
swh.mirror.forge-0.0.5.dist-info/METADATA
swh.mirror.forge-0.0.5.dist-info/WHEEL
swh.mirror.forge-0.0.5.dist-info/top_level.txt
swh.mirror.forge-0.0.5.dist-info/RECORD
