Metadata-Version: 2.1
Name: swh.mirror.forge
Version: 0.0.5
Summary: Mirror swhs forge to github
Home-page: https://forge.softwareheritage.org/source/swh-mirror-forge/
Author: Software Heritage developers
Author-email: swh-devel@inria.fr
License: UNKNOWN
Platform: UNKNOWN
Requires-Dist: vcversioner
Requires-Dist: requests
Requires-Dist: click
Requires-Dist: swh.core (>=0.0.29)
